marion/__init__.py
marion/admin.py
marion/apps.py
marion/defaults.py
marion/exceptions.py
marion/factories.py
marion/fields.py
marion/models.py
marion/serializers.py
marion/utils.py
marion/views.py
marion/issuers/__init__.py
marion/issuers/base.py
marion/issuers/dummy.py
marion/migrations/0001_initial.py
marion/migrations/0002_alter_documentrequest_issuer.py
marion/migrations/__init__.py
marion/static/marion/noun_Check_3612574.svg
marion/templates/marion/dummy.css
marion/templates/marion/dummy.html
marion/tests/__init__.py
marion/tests/test_defaults.py
marion/tests/test_fields.py
marion/tests/test_models.py
marion/tests/test_serializers.py
marion/tests/test_utils.py
marion/tests/test_views.py
marion/tests/issuers/__init__.py
marion/tests/issuers/test_base.py
marion/urls/__init__.py
marion/urls/debug.py
django_marion-0.6.0.dist-info/METADATA
django_marion-0.6.0.dist-info/WHEEL
django_marion-0.6.0.dist-info/top_level.txt
django_marion-0.6.0.dist-info/zip-safe
django_marion-0.6.0.dist-info/RECORD
