Metadata-Version: 2.1
Name: django-marion
Version: 0.6.0
Summary: The documents factory
Home-page: https://openfun.github.io/marion/
Author: Open FUN (France Universite Numerique)
Author-email: fun.dev@fun-mooc.fr
License: MIT
Keywords: Django,LMS,learning,PDF
Classifier: Development Status :: 4 - Beta
Classifier: Framework :: Django
Classifier: Framework :: Django :: 3.1
Classifier: Framework :: Django :: 3.2
Classifier: Intended Audience :: Developers
Classifier: License :: OSI Approved :: MIT License
Classifier: Natural Language :: English
Classifier: Programming Language :: Python :: 3
Classifier: Programming Language :: Python :: 3.8
Requires-Dist: arrow >=1.0.0
Requires-Dist: djangorestframework >=3.12.0
Requires-Dist: pydantic >=2.2.0
Requires-Dist: WeasyPrint >=59.0
Provides-Extra: ci
Requires-Dist: twine ==4.0.2 ; extra == 'ci'
Provides-Extra: dev
Requires-Dist: bandit ==1.7.5 ; extra == 'dev'
Requires-Dist: black ==23.9.1 ; extra == 'dev'
Requires-Dist: factory-boy ==3.3.0 ; extra == 'dev'
Requires-Dist: flake8 ==6.1.0 ; extra == 'dev'
Requires-Dist: hypothesis[django] ==6.86.1 ; extra == 'dev'
Requires-Dist: isort ==5.12.0 ; extra == 'dev'
Requires-Dist: Jinja2 ==3.1.2 ; extra == 'dev'
Requires-Dist: mkdocs ==1.5.2 ; extra == 'dev'
Requires-Dist: mkdocs-material ==9.3.1 ; extra == 'dev'
Requires-Dist: mkdocstrings ==0.23.0 ; extra == 'dev'
Requires-Dist: pdfminer.six ==20221105 ; extra == 'dev'
Requires-Dist: pyfakefs ==5.2.4 ; extra == 'dev'
Requires-Dist: pylint ==2.17.5 ; extra == 'dev'
Requires-Dist: pylint-django ==2.5.3 ; extra == 'dev'
Requires-Dist: pytest ==7.4.2 ; extra == 'dev'
Requires-Dist: pytest-cov ==4.1.0 ; extra == 'dev'
Requires-Dist: pytest-django ==4.5.2 ; extra == 'dev'
Provides-Extra: sandbox
Requires-Dist: Django ==4.2.5 ; extra == 'sandbox'
Requires-Dist: django-configurations ==2.4.1 ; extra == 'sandbox'
Requires-Dist: psycopg2-binary ==2.9.7 ; extra == 'sandbox'
